CHANGELOG.txt
LICENCE.txt
MANIFEST.in
README.txt
setup.py
Dev_Log_Tester/__init__.py
Dev_Log_Tester.egg-info/PKG-INFO
Dev_Log_Tester.egg-info/SOURCES.txt
Dev_Log_Tester.egg-info/dependency_links.txt
Dev_Log_Tester.egg-info/requires.txt
Dev_Log_Tester.egg-info/top_level.txt